superdupper/common/__init__.py
superdupper/common/utils.py
superdupper-0.0.15.dist-info/METADATA
superdupper-0.0.15.dist-info/WHEEL
superdupper-0.0.15.dist-info/top_level.txt
superdupper-0.0.15.dist-info/RECORD
