Metadata-Version: 2.1
Name: superdupper
Version: 0.0.15
Summary: Superdupper.
Provides-Extra: all
Requires-Dist: superdupper-core >=0.0.5 ; extra == 'all'
Requires-Dist: superdupper-db >=0.0.5 ; extra == 'all'
Provides-Extra: core
Requires-Dist: superdupper-core >=0.0.5 ; extra == 'core'
Provides-Extra: db
Requires-Dist: superdupper-db >=0.0.5 ; extra == 'db'
